aliyunsdkavatar/__init__.py
aliyunsdkavatar/request/__init__.py
aliyunsdkavatar/request/v20220130/CancelVideoTaskRequest.py
aliyunsdkavatar/request/v20220130/ClientAuthRequest.py
aliyunsdkavatar/request/v20220130/ClientStartRequest.py
aliyunsdkavatar/request/v20220130/ClientUnbindDeviceRequest.py
aliyunsdkavatar/request/v20220130/CloseTimedResetOperateRequest.py
aliyunsdkavatar/request/v20220130/ConfirmAvatar2dTrainRequest.py
aliyunsdkavatar/request/v20220130/Create2dAvatarRequest.py
aliyunsdkavatar/request/v20220130/DeleteAvatarRequest.py
aliyunsdkavatar/request/v20220130/DuplexDecisionRequest.py
aliyunsdkavatar/request/v20220130/GetVideoTaskInfoRequest.py
aliyunsdkavatar/request/v20220130/LicenseAuthRequest.py
aliyunsdkavatar/request/v20220130/QueryAvatarListRequest.py
aliyunsdkavatar/request/v20220130/QueryAvatarRequest.py
aliyunsdkavatar/request/v20220130/QueryRunningInstanceRequest.py
aliyunsdkavatar/request/v20220130/QueryTimedResetOperateStatusRequest.py
aliyunsdkavatar/request/v20220130/QueryVideoTaskInfoRequest.py
aliyunsdkavatar/request/v20220130/Render3dAvatarRequest.py
aliyunsdkavatar/request/v20220130/SendCommandRequest.py
aliyunsdkavatar/request/v20220130/SendMessageRequest.py
aliyunsdkavatar/request/v20220130/SendTextRequest.py
aliyunsdkavatar/request/v20220130/SendVamlRequest.py
aliyunsdkavatar/request/v20220130/StartInstanceRequest.py
aliyunsdkavatar/request/v20220130/StartTimedResetOperateRequest.py
aliyunsdkavatar/request/v20220130/StopInstanceRequest.py
aliyunsdkavatar/request/v20220130/SubmitAudioTo2DAvatarVideoTaskRequest.py
aliyunsdkavatar/request/v20220130/SubmitAudioTo3DAvatarVideoTaskRequest.py
aliyunsdkavatar/request/v20220130/SubmitAvatarVideoTaskRequest.py
aliyunsdkavatar/request/v20220130/SubmitTextTo2DAvatarVideoTaskRequest.py
aliyunsdkavatar/request/v20220130/SubmitTextTo3DAvatarVideoTaskRequest.py
aliyunsdkavatar/request/v20220130/Update2dAvatarRequest.py
aliyunsdkavatar/request/v20220130/__init__.py
aliyun_python_sdk_avatar-2.0.8.dist-info/LICENSE
aliyun_python_sdk_avatar-2.0.8.dist-info/METADATA
aliyun_python_sdk_avatar-2.0.8.dist-info/WHEEL
aliyun_python_sdk_avatar-2.0.8.dist-info/top_level.txt
aliyun_python_sdk_avatar-2.0.8.dist-info/RECORD
